__init__.py
etl_package_maiyo008/__init__.py
etl_package_maiyo008/etl.py
etl_package_maiyo008-0.0.2.dist-info/licenses/LICENSE
etl_package_maiyo008-0.0.2.dist-info/METADATA
etl_package_maiyo008-0.0.2.dist-info/WHEEL
etl_package_maiyo008-0.0.2.dist-info/top_level.txt
etl_package_maiyo008-0.0.2.dist-info/RECORD
