Metadata-Version: 2.4
Name: etl_package_maiyo008
Version: 0.0.2
Summary: An update to ETL package that loads data from API, cleans and loads it to a csv
Author-email: tony maiyo <tonymaiyo008@gmail.com>
License-Expression: MIT
Project-URL: Homepage, https://github.com/maiyo008/data_engineering_projects/tree/main/etl_project_1
Project-URL: Issues, https://github.com/maiyo008/data_engineering_projects/issues
Classifier: Programming Language :: Python :: 3
Classifier: Operating System :: OS Independent
Requires-Python: >=3.12
License-File: LICENSE
Dynamic: license-file
